pymedit/P0.py
pymedit/P0_3D.py
pymedit/P1.py
pymedit/P1Frac.py
pymedit/P1_3D.py
pymedit/__init__.py
pymedit/abstract.py
pymedit/mesh.py
pymedit/mesh3D.py
pymedit/utils/__init__.py
pymedit/utils/external.py
pymedit/utils/frac_sol.py
pymedit/utils/graphs.py
pymedit/utils/partition.py
pymedit/utils/pyvista.py
pymedit/utils/timing.py
pymedit-1.6.dist-info/licenses/LICENSE
pymedit-1.6.dist-info/METADATA
pymedit-1.6.dist-info/WHEEL
pymedit-1.6.dist-info/top_level.txt
pymedit-1.6.dist-info/RECORD
