Metadata-Version: 2.4
Name: pymedit
Version: 1.6
Summary: Package pymedit for operating on 2D and 3D meshes in the INRIA mesh format
Home-page: https://gitlab.com/florian.feppon/pymedit
Author: Florian Feppon
Author-email: florian.feppon@polytechnique.edu
License: GNU GPL version 3
Keywords: pymedit,mesh
Classifier: Programming Language :: Python :: 3
Classifier: License :: OSI Approved :: GNU General Public License v3 (GPLv3)
Classifier: Operating System :: OS Independent
Classifier: Topic :: Scientific/Engineering :: Mathematics
Requires-Python: >=3.6
License-File: LICENSE
Requires-Dist: numpy>=1.12.1
Requires-Dist: scipy>=0.19.1
Requires-Dist: colored>=1.3.93
Requires-Dist: matplotlib>=2.0.2
Requires-Dist: pyvista>=0.46.2
Dynamic: author
Dynamic: author-email
Dynamic: classifier
Dynamic: description
Dynamic: description-content-type
Dynamic: home-page
Dynamic: keywords
Dynamic: license
Dynamic: license-file
Dynamic: requires-dist
Dynamic: requires-python
Dynamic: summary
